<?xml version="1.0" encoding="UTF-8" standalone="yes"?>
<AssignMessage async="false" continueOnError="false" enabled="true" name="AM-ErrorMessageValidateCodeSubstatus">
    <DisplayName>AM-ErrorMessageValidateCodeSubstatus</DisplayName>
    <AssignVariable>
        <Name>errorMessage.status</Name>
        <Value>400</Value>
    </AssignVariable>
    <AssignVariable>
        <Name>errorMessage.code</Name>
        <Ref>responseQuerySubStatus.returnCode</Ref>
    </AssignVariable>
    <AssignVariable>
        <Name>errorMessage.message</Name>
        <Ref>responseQuerySubStatus.returnMsg</Ref>
    </AssignVariable>
</AssignMessage>